pysimplesps/__init__.py
pysimplesps/__main__.py
pysimplesps/avpmed2json.py
pysimplesps/dmrt2json.py
pysimplesps/dmrt2topo.py
pysimplesps/links2json.py
pysimplesps/links2topo.py
pysimplesps-0.2.1.dist-info/METADATA
pysimplesps-0.2.1.dist-info/WHEEL
pysimplesps-0.2.1.dist-info/entry_points.txt
pysimplesps-0.2.1.dist-info/RECORD
