Metadata-Version: 2.4
Name: pysimplesps
Version: 0.2.1
Summary: A comprehensive Python library to parse SPS MML configurations and generate JSON/topology data
Project-URL: Homepage, https://github.com/fxyzbtc/pysimplesps
Project-URL: Repository, https://github.com/fxyzbtc/pysimplesps
Project-URL: Documentation, https://deepwiki.com/fxyzbtc/pysimplesps
Project-URL: Issues, https://github.com/fxyzbtc/pysimplesps/issues
Keywords: diameter,mml,signaling,sps,telecom,topology
Classifier: Development Status :: 4 - Beta
Classifier: Intended Audience :: Telecommunications Industry
Classifier: License :: OSI Approved :: MIT License
Classifier: Operating System :: OS Independent
Classifier: Programming Language :: Python :: 3
Classifier: Programming Language :: Python :: 3.12
Classifier: Topic :: Communications :: Telephony
Classifier: Topic :: System :: Networking
Classifier: Topic :: Utilities
Requires-Python: >=3.12
Requires-Dist: loguru>=0.7.3
Requires-Dist: pydantic>=2.0.0
Requires-Dist: tqdm>=4.66.0
Provides-Extra: dev
Requires-Dist: mypy>=1.8.0; extra == 'dev'
Requires-Dist: pytest-cov>=4.0.0; extra == 'dev'
Requires-Dist: pytest>=8.3.5; extra == 'dev'
Requires-Dist: ruff>=0.6.0; extra == 'dev'
